agent_http.py
setup.cfg
setup.py
agent.http.egg-info/PKG-INFO
agent.http.egg-info/SOURCES.txt
agent.http.egg-info/dependency_links.txt
agent.http.egg-info/entry_points.txt
agent.http.egg-info/requires.txt
agent.http.egg-info/top_level.txt