Metadata-Version: 1.0
Name: agent.http
Version: 0.3.1
Summary: Rackspace Monitoring agent.plugin HTTP check
Home-page: https://github.com/vickleford/agent.http
Author: Vic Watkins
Author-email: vic.watkins@rackspace.com
License: UNKNOWN
Platform: UNKNOWN
